gamedata.py
data/gamedata.py
GreenBean-0.1.0.dist-info/METADATA
GreenBean-0.1.0.dist-info/WHEEL
GreenBean-0.1.0.dist-info/top_level.txt
GreenBean-0.1.0.dist-info/RECORD
