Metadata-Version: 2.1
Name: GreenBean
Version: 0.1.0
Summary: A library for saving game data.
Author: Bob Robertson
Author-email: coderdude123@proton.me
Classifier: Programming Language :: Python :: 3
Classifier: License :: OSI Approved :: MIT License
Classifier: Operating System :: OS Independent
Requires-Python: >=3.6
